outatime/__init__.py
outatime/_version.py
outatime/dataclass/__init__.py
outatime/dataclass/time_series_data.py
outatime/granularity/__init__.py
outatime/granularity/granularity.py
outatime/granularity/granularity_factory.py
outatime/granularity/utils.py
outatime/timeseries/__init__.py
outatime/timeseries/batches.py
outatime/timeseries/expr.py
outatime/timeseries/filter_parser.py
outatime/timeseries/inference.py
outatime/timeseries/time_series.py
outatime/util/__init__.py
outatime/util/agenda.py
outatime/util/bisect.py
outatime/util/decorators.py
outatime/util/relativedelta.py
test/__init__.py
test/test_agenda.py
test/test_batch_aggregate.py
test/test_batch_pick_a_day.py
test/test_batch_pick_a_weekday.py
test/test_batch_split.py
test/test_bisect.py
test/test_expr.py
test/test_granularity.py
test/test_granularity_factory.py
test/test_granularity_utils.py
test/test_inference.py
test/test_time_series.py
test/test_time_series_query.py
test/test_time_series_resample.py
test/test_utils_bisect.py
test/test_utils_relativedelta.py
test/utils.py
outatime-3.2.2.dist-info/AUTHORS.rst
outatime-3.2.2.dist-info/LICENSE
outatime-3.2.2.dist-info/METADATA
outatime-3.2.2.dist-info/WHEEL
outatime-3.2.2.dist-info/top_level.txt
outatime-3.2.2.dist-info/RECORD
