Metadata-Version: 2.1
Name: outatime
Version: 3.2.2
Summary: Python framework to manage time series
Home-page: https://github.com/SynStratos/outatime
Author: Luca Spartera
Author-email: synstratos.dev@gmail.com
Keywords: time series,ts,timeseries,temporal data
Classifier: Programming Language :: Python :: 3
Classifier: Programming Language :: Python :: 3.8
Classifier: Programming Language :: Python :: 3.9
Classifier: Programming Language :: Python :: 3.10
Classifier: License :: OSI Approved :: MIT License
Classifier: Operating System :: OS Independent
Classifier: Natural Language :: English
Requires-Python: >=3.8, <3.11
License-File: LICENSE
License-File: AUTHORS.rst
Requires-Dist: python-dateutil
Requires-Dist: statsmodels
Requires-Dist: numpy
Requires-Dist: scipy
Requires-Dist: lark
